setup.py
keypool/__init__.py
keypool.egg-info/PKG-INFO
keypool.egg-info/SOURCES.txt
keypool.egg-info/dependency_links.txt
keypool.egg-info/top_level.txt