Metadata-Version: 1.0
Name: keypool
Version: 0.1
Summary: Classes and helpers to generate and maintain a pool of unique integer keys.
Home-page: https://github.com/tyrannosaur/keypool
Author: Charlie Liban
Author-email: charlie@tyrannosaur.ca
License: MIT License
Download-URL: https://github.com/tyrannosaur/keypool/zipball/master
Keywords: data structures
Platform: UNKNOWN
Classifier: Programming Language :: Python
Classifier: License :: OSI Approved :: MIT License
